{
  "insertId": "1g3rwof4gs8",
  "jsonPayload": {
    "eventType": "GCE_OPERATION_DONE",
    "resource": {
      "type": "gce_instance",
      "labels": {
        "instance_id": "8912345678901234567",
        "zone": "us-central1-a",
        "project_id": "my-gcp-project"
      }
    },
    "operation": {
      "id": "operation-1557553092567-5ae4b17f50e15-4739ed0e-aac44",
      "operationType": "insert",
      "status": "DONE"
    },
    "user": "user@example.com",
    "timestamp": "2024-10-07T14:10:36Z"
  }
}
{
  "insertId": "kfj28doiajh",
  "httpRequest": {
    "requestMethod": "GET",
    "requestUrl": "/api/resource",
    "status": 200,
    "userAgent": "Mozilla/5.0",
    "remoteIp": "203.0.113.10"
  },
  "jsonPayload": {
    "message": "API request successful"
  },
  "resource": {
    "type": "gce_instance",
    "labels": {
      "instance_id": "8912345678901234567",
      "zone": "us-central1-a",
      "project_id": "my-gcp-project"
    }
  },
  "timestamp": "2024-10-07T14:12:05Z"
}
{
  "insertId": "8dsf3sf43r",
  "textPayload": "Failed login attempt for user admin",
  "severity": "WARNING",
  "resource": {
    "type": "gce_instance",
    "labels": {
      "instance_id": "8912345678901234567",
      "zone": "us-central1-a",
      "project_id": "my-gcp-project"
    }
  },
  "timestamp": "2024-10-07T14:15:10Z"
}
{
  "insertId": "sdf45wew43r",
  "jsonPayload": {
    "eventType": "GCS_OBJECT_ACCESS",
    "bucketName": "my-bucket",
    "objectName": "example.txt",
    "action": "READ",
    "user": "user@example.com"
  },
  "resource": {
    "type": "gcs_bucket",
    "labels": {
      "project_id": "my-gcp-project"
    }
  },
  "timestamp": "2024-10-07T14:18:22Z"
}
{
  "insertId": "98r43fdsfa",
  "jsonPayload": {
    "eventType": "VPC_NETWORK_ACTIVITY",
    "network": "default",
    "action": "ALLOW",
    "sourceIp": "203.0.113.20",
    "destinationIp": "10.0.0.1",
    "protocol": "TCP"
  },
  "resource": {
    "type": "gce_instance",
    "labels": {
      "instance_id": "8912345678901234567",
      "zone": "us-central1-a",
      "project_id": "my-gcp-project"
    }
  },
  "timestamp": "2024-10-07T14:20:18Z"
}
{
  "insertId": "kjsaf843df",
  "jsonPayload": {
    "eventType": "BIGQUERY_QUERY_RUN",
    "query": "SELECT * FROM dataset.table",
    "user": "user@example.com",
    "status": "SUCCESS"
  },
  "resource": {
    "type": "bigquery_dataset",
    "labels": {
      "project_id": "my-gcp-project"
    }
  },
  "timestamp": "2024-10-07T14:22:55Z"
}
{
  "insertId": "p3we23rfr",
  "httpRequest": {
    "requestMethod": "POST",
    "requestUrl": "/api/create",
    "status": 201,
    "userAgent": "Mozilla/5.0",
    "remoteIp": "198.51.100.5"
  },
  "jsonPayload": {
    "message": "Resource created successfully"
  },
  "resource": {
    "type": "gce_instance",
    "labels": {
      "instance_id": "8912345678901234567",
      "zone": "us-central1-a",
      "project_id": "my-gcp-project"
    }
  },
  "timestamp": "2024-10-07T14:25:30Z"
}
{
  "insertId": "l3k53ke3r",
  "jsonPayload": {
    "eventType": "CLOUD_FUNCTION_INVOCATION",
    "functionName": "my-cloud-function",
    "status": "SUCCESS",
    "invocationType": "HTTP"
  },
  "resource": {
    "type": "cloud_function",
    "labels": {
      "project_id": "my-gcp-project"
    }
  },
  "timestamp": "2024-10-07T14:27:45Z"
}
{
  "insertId": "mwe8w3e9r",
  "jsonPayload": {
    "eventType": "PUBSUB_MESSAGE_PUBLISHED",
    "topicName": "projects/my-gcp-project/topics/my-topic",
    "messageId": "1234567890123456"
  },
  "resource": {
    "type": "pubsub_topic",
    "labels": {
      "project_id": "my-gcp-project"
    }
  },
  "timestamp": "2024-10-07T14:30:12Z"
}
{
  "insertId": "msds23oikm",
  "jsonPayload": {
    "eventType": "IAM_ROLE_GRANTED",
    "roleName": "roles/viewer",
    "user": "user@example.com",
    "status": "SUCCESS"
  },
  "resource": {
    "type": "iam_role",
    "labels": {
      "project_id": "my-gcp-project"
    }
  },
  "timestamp": "2024-10-07T14:32:47Z"
}
{
  "insertId": "psdkf24we",
  "jsonPayload": {
    "eventType": "CLOUD_STORAGE_UPLOAD",
    "bucketName": "my-bucket",
    "objectName": "new-file.csv",
    "user": "admin@example.com"
  },
  "resource": {
    "type": "gcs_bucket",
    "labels": {
      "project_id": "my-gcp-project"
    }
  },
  "timestamp": "2024-10-07T14:35:23Z"
}
{
  "insertId": "sdfwe34fs",
  "jsonPayload": {
    "eventType": "FIRESTORE_DOCUMENT_WRITE",
    "documentPath": "projects/my-gcp-project/databases/(default)/documents/collection/doc1",
    "operation": "CREATE",
    "user": "user@example.com"
  },
  "resource": {
    "type": "firestore_document",
    "labels": {
      "project_id": "my-gcp-project"
    }
  },
  "timestamp": "2024-10-07T14:37:16Z"
}
{
  "insertId": "kjsaf343df",
  "jsonPayload": {
    "eventType": "VPC_NETWORK_ACTIVITY",
    "network": "default",
    "action": "DENY",
    "sourceIp": "198.51.100.5",
    "destinationIp": "10.0.0.1",
    "protocol": "TCP"
  },
  "resource": {
    "type": "gce_instance",
    "labels": {
      "instance_id": "8912345678901234567",
      "zone": "us-central1-a",
      "project_id": "my-gcp-project"
    }
  },
  "timestamp": "2024-10-07T14:40:05Z"
}
{
  "insertId": "mnfb3gsf5r",
  "httpRequest": {
    "requestMethod": "GET",
    "requestUrl": "/api/resource",
    "status": 200,
    "userAgent": "Mozilla/5.0",
    "remoteIp": "192.0.2.5"
  },
  "jsonPayload": {
    "message": "API request successful"
  },
  "resource": {
    "type": "gce_instance",
    "labels": {
      "instance_id": "8912345678901234567",
      "zone": "us-central1-a",
      "project_id": "my-gcp-project"
    }
  },
  "timestamp": "2024-10-07T14:42:12Z"
}
{
  "insertId": "kj45lfsdf4",
  "jsonPayload": {
    "eventType": "BIGQUERY_QUERY_RUN",
    "query": "SELECT COUNT(*) FROM dataset.table",
    "user": "admin@example.com",
    "status": "SUCCESS"
  },
  "resource": {
    "type": "bigquery_dataset",
    "labels": {
      "project_id": "my-gcp-project"
    }
  },
  "timestamp": "2024-10-07T14:45:23Z"
}
{
  "insertId": "d3r9j8o2je",
  "jsonPayload": {
    "eventType": "CLOUD_FUNCTION_INVOCATION",
    "functionName": "my-function",
    "status": "FAILURE",
    "invocationType": "HTTP"
  },
  "resource": {
    "type": "cloud_function",
    "labels": {
      "project_id": "my-gcp-project"
    }
  },
  "timestamp": "2024-10-07T14:47:48Z"
}
{
  "insertId": "jkrfwe43fs",
  "jsonPayload": {
    "eventType": "GCE_OPERATION_DONE",
    "resource": {
      "type": "gce_instance",
      "labels": {
        "instance_id": "8912345678901234567",
        "zone": "us-central1-a",
        "project_id": "my-gcp-project"
      }
    },
    "operation": {
      "id": "operation-1557553092567-5ae4b17f50e15-4739ed0e-aac44",
      "operationType": "terminate",
      "status": "DONE"
    },
    "user": "user@example.com",
    "timestamp": "2024-10-07T14:50:12Z"
  }
}
{
  "insertId": "we34lfkasd",
  "jsonPayload": {
    "eventType": "IAM_POLICY_UPDATED",
    "policyName": "my-policy",
    "user": "admin@example.com",
    "status": "SUCCESS"
  },
  "resource": {
    "type": "iam_policy",
    "labels": {
      "project_id": "my-gcp-project"
    }
  },
  "timestamp": "2024-10-07T14:52:05Z"
}
{
  "insertId": "sdfg43rk2",
  "jsonPayload": {
    "eventType": "PUBSUB_MESSAGE_PUBLISHED",
    "topicName": "projects/my-gcp-project/topics/my-topic",
    "messageId": "6789012345678901"
  },
  "resource": {
    "type": "pubsub_topic",
    "labels": {
      "project_id": "my-gcp-project"
    }
  },
  "timestamp": "2024-10-07T14:54:22Z"
}
{
  "insertId": "sdf34lfk4",
  "jsonPayload": {
    "eventType": "VPC_NETWORK_ACTIVITY",
    "network": "custom-network",
    "action": "ALLOW",
    "sourceIp": "198.51.100.10",
    "destinationIp": "10.0.1.5",
    "protocol": "UDP"
  },
  "resource": {
    "type": "gce_instance",
    "labels": {
      "instance_id": "8912345678901234567",
      "zone": "us-central1-a",
      "project_id": "my-gcp-project"
    }
  },
  "timestamp": "2024-10-07T14:57:10Z"
}